mpsky/__init__.py
mpsky/_version.py
mpsky/core.py
mpsky/log_conf.yaml
mpsky/service.py
mpsky-0.0.2.dist-info/LICENSE
mpsky-0.0.2.dist-info/METADATA
mpsky-0.0.2.dist-info/WHEEL
mpsky-0.0.2.dist-info/entry_points.txt
mpsky-0.0.2.dist-info/top_level.txt
mpsky-0.0.2.dist-info/RECORD
