Metadata-Version: 2.1
Name: mpsky
Version: 0.0.2
Author-email: Mario Juric <mjuric@astro.washington.edu>
License: BSD 3-Clause License
Project-URL: Source Code, https://github.com/mjuric/mpsky
Classifier: Development Status :: 4 - Beta
Classifier: License :: OSI Approved :: BSD License
Classifier: Intended Audience :: Developers
Classifier: Intended Audience :: Science/Research
Classifier: Operating System :: OS Independent
Classifier: Programming Language :: Python
Requires-Python: >=3.9
License-File: LICENSE
Requires-Dist: tables
Requires-Dist: tqdm
Requires-Dist: pyarrow
Requires-Dist: healpy
Requires-Dist: pydantic-settings
Requires-Dist: astropy
Requires-Dist: pandas
Requires-Dist: requests
Requires-Dist: uvicorn
Requires-Dist: fastapi
Provides-Extra: dev
Requires-Dist: asv ==0.6.1 ; extra == 'dev'
Requires-Dist: jupyter ; extra == 'dev'
Requires-Dist: pre-commit ; extra == 'dev'
Requires-Dist: pytest ; extra == 'dev'
Requires-Dist: pytest-cov ; extra == 'dev'
